zosedit/__init__.py
zosedit/constants.py
zosedit/main.py
zosedit/models.py
zosedit/zftp.py
zosedit/gui/__init__.py
zosedit/gui/dialog.py
zosedit/gui/editor.py
zosedit/gui/explorer.py
zosedit-0.0.15.dist-info/METADATA
zosedit-0.0.15.dist-info/WHEEL
zosedit-0.0.15.dist-info/entry_points.txt
zosedit-0.0.15.dist-info/top_level.txt
zosedit-0.0.15.dist-info/RECORD
